pulumi_http/__init__.py
pulumi_http/_inputs.py
pulumi_http/_utilities.py
pulumi_http/get_http.py
pulumi_http/outputs.py
pulumi_http/provider.py
pulumi_http/pulumi-plugin.json
pulumi_http/py.typed
pulumi_http-0.1.3.dist-info/METADATA
pulumi_http-0.1.3.dist-info/WHEEL
pulumi_http-0.1.3.dist-info/top_level.txt
pulumi_http-0.1.3.dist-info/RECORD
